[{"Updated": "February 13, 2007 12:01:00 PM", "x_title": "AntiPascal.1101", "x_link": "http://www.symantec.com/security_response/writeup.jsp?docid=2003-051613-2951-99", "Writeup By": "Maryl Magee", "Discovered": "May 16, 2003", "Systems Affected": "Windows", "x_pubDate": "May 18, 2003", "Type": "Virus", "x_description": "Type: Virus"}, {"Updated": "February 13, 2007 12:01:05 PM", "x_title": "AntiPascal.408", "x_link": "http://www.symantec.com/security_response/writeup.jsp?docid=2003-050714-1658-99", "Writeup By": "Maryl Magee", "Discovered": "May 07, 2003", "Systems Affected": "Windows", "x_pubDate": "May 07, 2003", "Type": "Virus", "x_description": "Type: Virus"}, {"Updated": "January 18, 2008 5:19:02 PM", "x_title": "AntiSpyBoss", "x_link": "http://www.symantec.com/security_response/writeup.jsp?docid=2008-011816-5128-99", "Risk Impact": "Medium", "Version": "1.0.0.44", "Systems Affected": "Windows", "x_pubDate": "Jan 18, 2008", "Type": "Misleading Application", "x_description": "Type: Misleading Application", "Name": "AntiSpyBoss"}, {"Publisher": "AntiSpyCheck.com", "Updated": "January 11, 2008 12:58:40 PM", "x_title": "AntiSpyCheck", "x_link": "http://www.symantec.com/security_response/writeup.jsp?docid=2008-011112-3720-99", "Risk Impact": "Medium", "Version": "2.1", "Systems Affected": "Windows", "x_pubDate": "Jan 11, 2008", "Type": "Misleading Application", "x_description": "Type: Misleading Application", "Name": "AntiSpyCheck"}, {"Publisher": "antispywaredeluxe.com", "Updated": "March 26, 2008 2:07:26 PM", "x_title": "AntispyDeluxe", "x_link": "http://www.symantec.com/security_response/writeup.jsp?docid=2008-032613-0743-99", "Risk Impact": "Medium", "Version": "1.53", "Systems Affected": "Windows", "x_pubDate": "Mar 26, 2008", "Type": "Misleading Application", "x_description": "Type: Misleading Application", "Name": "AntispywareDeluxe"}, {"Updated": "October 31, 2007 12:39:36 PM", "x_title": "AntiSpyGuard", "x_link": "http://www.symantec.com/security_response/writeup.jsp?docid=2007-103112-1058-99", "Risk Impact": "High", "Systems Affected": "Windows", "x_pubDate": "Oct 31, 2007", "Type": "Misleading Application", "x_description": "Type: Misleading Application", "Name": "AntiSpyGuard"}, {"Publisher": "AntiSpyKit.com", "Updated": "February 22, 2008 2:02:13 PM", "x_title": "AntiSpyKit", "x_link": "http://www.symantec.com/security_response/writeup.jsp?docid=2008-022110-2028-99", "Risk Impact": "Medium", "Version": "1.0.0.1", "Systems Affected": "Windows", "x_pubDate": "Feb 19, 2008", "Type": "Misleading Application", "x_description": "Type: Misleading Application", "Name": "AntiSpyKit 5.2"}, {"Updated": "December 05, 2007 4:37:50 PM", "x_title": "AntiSpyPro", "x_link": "http://www.symantec.com/security_response/writeup.jsp?docid=2007-120516-0822-99", "Risk Impact": "Medium", "Version": "2.4.0.0", "Systems Affected": "Windows", "x_pubDate": "Dec 05, 2007", "Type": "Misleading Application", "x_description": "Type: Misleading Application", "Name": "AntiSpyPro"}, {"Publisher": "PrivSoft Inc.", "Updated": "March 26, 2008 7:27:46 AM", "x_title": "AntispySpider", "x_link": "http://www.symantec.com/security_response/writeup.jsp?docid=2008-032605-1537-99", "Risk Impact": "Medium", "Version": "1.2", "Infection Length": "2,049,024 bytes", "x_pubDate": "Mar 26, 2008", "Systems Affected": "Windows", "Type": "Misleading Application", "x_description": "Type: Misleading Application", "Name": "AntispySpider"}, {"Publisher": "AntiSpywareExpert Inc.", "Updated": "April 11, 2008 9:58:17 AM", "x_title": "AntiSpywareExpert", "x_link": "http://www.symantec.com/security_response/writeup.jsp?docid=2008-041109-4254-99", "Risk Impact": "Medium", "Version": "1.0.7.1", "Systems Affected": "Windows", "x_pubDate": "Apr 11, 2008", "Type": "Misleading Application", "x_description": "Type: Misleading Application", "Name": "AntiSpywareExpert"}]